geode/__init__.py
geode/datasets.py
geode/losses.py
geode/models.py
geode/utilities.py
geode_ml-2.7.2.dist-info/LICENSE
geode_ml-2.7.2.dist-info/METADATA
geode_ml-2.7.2.dist-info/WHEEL
geode_ml-2.7.2.dist-info/top_level.txt
geode_ml-2.7.2.dist-info/RECORD
