Metadata-Version: 2.1
Name: geode-ml
Version: 2.7.2
Summary: Classes and methods to help with the creation of geospatial training datasets and deep-learning models.
Author-email: Matt Reichenbach <matthew.reichenbach@gmail.com>
License: MIT License
Project-URL: Homepage, https://github.com/mpreichenbach/geode-ml
Keywords: deep-learning,training,dataset,geospatial
Classifier: License :: OSI Approved :: MIT License
Classifier: Programming Language :: Python
Classifier: Programming Language :: Python :: 3
Classifier: Operating System :: OS Independent
Requires-Python: >=3.7
License-File: LICENSE
Requires-Dist: gdal (>=3.4)
Requires-Dist: numpy
Requires-Dist: scikit-learn
Requires-Dist: tensorflow (>=2.7) ; platform_system == "Linux"
Requires-Dist: tensorflow-gpu (>=2.7) ; platform_system == "Windows"
